td_ml_autosegmentation/.DS_Store
td_ml_autosegmentation/__init__.py
td_ml_autosegmentation/as_obj.py
td_ml_autosegmentation/autosegment.py
td_ml_autosegmentation-1.0.18.dist-info/METADATA
td_ml_autosegmentation-1.0.18.dist-info/WHEEL
td_ml_autosegmentation-1.0.18.dist-info/licenses/LICENSE
td_ml_autosegmentation-1.0.18.dist-info/RECORD
