Metadata-Version: 2.1
Name: td_ml_autosegmentation
Version: 1.0.18
Summary: TD Autosegmentation
Project-URL: Homepage, https://github.com/treasure-data-ps/ml_autosegmentation
Project-URL: Bug Tracker, https://github.com/treasure-data-ps/ml_autosegmentation
Author-email: Yish Lim <limyishuen@gmail.com>
License-File: LICENSE
Classifier: Operating System :: OS Independent
Classifier: Programming Language :: Python :: 3
Requires-Python: >=3.8
